harmonia/__init__.py
harmonia/conftest.py
harmonia/utils.py
harmonia/algorithms/__init__.py
harmonia/algorithms/arrays.py
harmonia/algorithms/bases.py
harmonia/algorithms/discretisation.py
harmonia/algorithms/integration.py
harmonia/cosmology/__init__.py
harmonia/cosmology/geometry.py
harmonia/cosmology/scale_dependence.py
harmonia/mapper/__init__.py
harmonia/mapper/catalogue_maker.py
harmonia/mapper/map_transform.py
harmonia/reader/__init__.py
harmonia/reader/_kernels.py
harmonia/reader/couplings.py
harmonia/reader/likelihoods.py
harmonia/reader/models.py
harmonia/surveyor/__init__.py
harmonia/surveyor/coordinates.py
harmonia/surveyor/definition.py
harmonia/surveyor/synthesis.py
harmonia/tests/__init__.py
harmonia/tests/test_arrays.py
harmonia/tests/test_bases.py
harmonia/tests/test_catalogue_maker.py
harmonia/tests/test_coordinates.py
harmonia/tests/test_definition.py
harmonia/tests/test_discretisation.py
harmonia/tests/test_geometry.py
harmonia/tests/test_integration.py
harmonia/tests/test_likelihoods.py
harmonia/tests/test_synthesis.py
harmonia/tests/test_utils.py
HarmoniaCosmo-0.1.2.dist-info/LICENCE
HarmoniaCosmo-0.1.2.dist-info/METADATA
HarmoniaCosmo-0.1.2.dist-info/WHEEL
HarmoniaCosmo-0.1.2.dist-info/top_level.txt
HarmoniaCosmo-0.1.2.dist-info/RECORD
