Metadata-Version: 2.1
Name: HarmoniaCosmo
Version: 0.1.2
Summary: Hybrid-basis inference for large-scale galaxy clustering.
Home-page: https://github.com/MikeSWang/Harmonia/
Author: Mike S Wang
Author-email: mike.wang@port.ac.uk
License: GPLv3
Project-URL: Documentation, https://mikeswang.github.io/Harmonia
Project-URL: Source, https://github.com/MikeSWang/Harmonia/
Platform: UNKNOWN
Classifier: Programming Language :: Python :: 3
Classifier: License :: OSI Approved :: GNU General Public License v3 (GPLv3)
Classifier: Operating System :: OS Independent
Requires-Python: >=3.6
Requires-Dist: numpy
Requires-Dist: scipy
Requires-Dist: mpi4py
Requires-Dist: astropy
Requires-Dist: healpy
Requires-Dist: nbodykit
Requires-Dist: tqdm
